AUTHORS
CHANGELOG.rst
LICENSE.txt
MANIFEST.in
README.rst
setup.py
BicycleParameters.egg-info/PKG-INFO
BicycleParameters.egg-info/SOURCES.txt
BicycleParameters.egg-info/dependency_links.txt
BicycleParameters.egg-info/entry_points.txt
BicycleParameters.egg-info/requires.txt
BicycleParameters.egg-info/top_level.txt
bicycleparameters/__init__.py
bicycleparameters/_mooreriderlean2012.py
bicycleparameters/app.py
bicycleparameters/bicycle.py
bicycleparameters/com.py
bicycleparameters/conversions.py
bicycleparameters/geometry.py
bicycleparameters/inertia.py
bicycleparameters/io.py
bicycleparameters/main.py
bicycleparameters/models.py
bicycleparameters/parameter_dicts.py
bicycleparameters/parameter_sets.py
bicycleparameters/period.py
bicycleparameters/plot.py
bicycleparameters/rider.py
bicycleparameters/tables.py
bicycleparameters/version.py
bicycleparameters/app-data/bicycles/Benchmark/Parameters/BenchmarkBenchmark.txt
bicycleparameters/app-data/bicycles/Browser/Parameters/BrowserBenchmark.txt
bicycleparameters/app-data/bicycles/Browserins/Parameters/BrowserinsBenchmark.txt
bicycleparameters/app-data/bicycles/Crescendo/Parameters/CrescendoBenchmark.txt
bicycleparameters/app-data/bicycles/Fisher/Parameters/FisherBenchmark.txt
bicycleparameters/app-data/bicycles/Pista/Parameters/PistaBenchmark.txt
bicycleparameters/app-data/bicycles/Rigid/Parameters/RigidBenchmark.txt
bicycleparameters/app-data/bicycles/Silver/Parameters/SilverBenchmark.txt
bicycleparameters/app-data/bicycles/Yellow/Parameters/YellowBenchmark.txt
bicycleparameters/app-data/bicycles/Yellowrev/Parameters/YellowrevBenchmark.txt
bicycleparameters/assets/app-explanation.md
bicycleparameters/assets/styles.css
bicycleparameters/tests/__init__.py
bicycleparameters/tests/test_bicycle.py
bicycleparameters/tests/test_bicycleparameters.py
bicycleparameters/tests/test_io.py
bicycleparameters/tests/test_models.py
bicycleparameters/tests/test_parameter_sets.py
bicycleparameters/tests/parameter_sets/benchmark-benchmark.yml
bicycleparameters/tests/parameter_sets/benchmark-browser.yml
bicycleparameters/tests/parameter_sets/benchmark-extendedoptc.yml
bicycleparameters/tests/parameter_sets/benchmark-pista.yml
