Metadata-Version: 2.2
Name: BicycleParameters
Version: 1.3.0
Summary: Generates and manipulates the physical parameters of a bicycle.
Home-page: https://bicycleparameters.readthedocs.io
Author: Jason K. Moore
Author-email: moorepants@gmail.com
License: LICENSE.txt
Project-URL: Documentation, http://bicycleparameters.readthedocs.io
Project-URL: Issue Tracker, https://github.com/moorepants/BicycleParameters/issues
Project-URL: Source Code, https://github.com/moorepants/BicycleParameters
Project-URL: Web Application, https://bicycle-dynamics.onrender.com
Classifier: Programming Language :: Python
Classifier: Programming Language :: Python :: 3.9
Classifier: Programming Language :: Python :: 3.10
Classifier: Programming Language :: Python :: 3.11
Classifier: Programming Language :: Python :: 3.12
Classifier: Programming Language :: Python :: 3.13
Classifier: Operating System :: OS Independent
Classifier: Development Status :: 5 - Production/Stable
Classifier: Intended Audience :: Science/Research
Classifier: License :: OSI Approved :: BSD License
Classifier: Natural Language :: English
Classifier: Topic :: Scientific/Engineering
Classifier: Topic :: Scientific/Engineering :: Physics
Requires-Python: >=3.9
License-File: LICENSE.txt
License-File: AUTHORS
Requires-Dist: DynamicistToolKit>=0.5.3
Requires-Dist: matplotlib>=3.5.1
Requires-Dist: numpy>=1.21.5
Requires-Dist: pyyaml>=5.4.1
Requires-Dist: scipy>=1.8.0
Requires-Dist: uncertainties>=3.1.5
Requires-Dist: yeadon>=1.3.0
Provides-Extra: doc
Requires-Dist: numpydoc>=1.2; extra == "doc"
Requires-Dist: sphinx-gallery; extra == "doc"
Requires-Dist: sphinx-reredirects; extra == "doc"
Requires-Dist: sphinx>=4.3.2; extra == "doc"
Provides-Extra: app
Requires-Dist: dash-bootstrap-components; extra == "app"
Requires-Dist: dash>=2; extra == "app"
Requires-Dist: pandas>=1.3.5; extra == "app"
Dynamic: author
Dynamic: author-email
Dynamic: classifier
Dynamic: description
Dynamic: home-page
Dynamic: license
Dynamic: project-url
Dynamic: provides-extra
Dynamic: requires-dist
Dynamic: requires-python
Dynamic: summary
